README.rst
setup.py
cmd/deer
sacreddeer/__init__.py
sacreddeer/sacred_deer_bot.py
sacreddeer.egg-info/PKG-INFO
sacreddeer.egg-info/SOURCES.txt
sacreddeer.egg-info/dependency_links.txt
sacreddeer.egg-info/not-zip-safe
sacreddeer.egg-info/requires.txt
sacreddeer.egg-info/top_level.txt