Metadata-Version: 1.0
Name: sacreddeer
Version: 1.3
Summary: Ask your stupid questions and Deer will answer
Home-page: http://github.com/pannkotsky/sacreddeer
Author: Valerii Kovalchuk
Author-email: kovvalole@gmail.com
License: MIT
Platform: UNKNOWN
